{
  "pagination": {
    "totalItems": 1000,
    "pageSize": 10,
    "pageIndex": 0,
    "pageCount": 100,
    "startFrom": 0
  },
  "newsFeed": [
    {
      "contentType": "Interview",
      "id": "_content_chelseafcennews20210911christensen--we-are-hungry-to-ke",
      "type": "NewsCard",
      "timestamp": "2021-09-11T11:30:00.000Z",
      "orderDate": "2021-09-11T11:30:00.000Z",
      "link": {
        "path": "/content/chelseafc/en/news/2021/09/11/christensen--we-are-hungry-to-keep-riding-this-wave",
        "type": "NewsCard",
        "title": "Christensen: We are hungry to keep riding this wave",
        "url": "https://prod-content-cdn.chelseafc.com/content/chelseafc/en/news/2021/09/11/christensen--we-are-hungry-to-keep-riding-this-wave.html",
        "external": true,
        "target": "sameWindow",
        "categories": [],
        "timestamp": "2021-09-11T11:30:00.000Z"
      },
      "template": "standard-article",
      "path": "/content/chelseafc/en/news/2021/09/11/christensen--we-are-hungry-to-keep-riding-this-wave",
      "media": {
        "type": "image-component",
        "image": {
          "type": "ImageCloudinary",
          "alt": "Andreas Christensen",
          "id": "editorial/news/2021/09/11/andreas-christensen-stock-21-22",
          "gravity": "auto",
          "aspectRatio": 1.4995146,
          "cropMode": "fill"
        }
      },
      "content": "Christensen: We are hungry to keep riding this wave",
      "publishDate": "2021-09-11T11:30:00.000Z",
      "url": "https://prod-content-cdn.chelseafc.com/content/chelseafc/en/news/2021/09/11/christensen--we-are-hungry-to-keep-riding-this-wave.html",
      "readTimeInMins": 7,
      "tags": [
        {
          "title": "Andreas Christensen",
          "namespace": "content-tag:",
          "id": "content-tag_person_player_andreas-christensen"
        },
        {
          "title": "Premier League",
          "namespace": "content-tag:",
          "id": "content-tag_competition_first-team-competitions_premier-league"
        },
        {
          "title": "Men",
          "namespace": "content-tag:",
          "id": "content-tag_team_men"
        },
        {
          "title": "Aston Villa",
          "namespace": "content-tag:",
          "id": "content-tag_team_opposition-teams_aston-villa"
        }
      ],
      "date": "2021-09-11T11:30:00.000Z",
      "description": "Andreas Christensen is aware of the positive feeling around the club following our recent European successes, and the defender wants to help ensure that momentum is maintained as we head into a busy spell of fixtures.",
      "matchId": 2210303
    },
    {
      "contentType": "News",
      "id": "_content_chelseafcennews20210911thiago-silva-cleared-for-chelsea",
      "type": "NewsCard",
      "timestamp": "2021-09-11T09:09:00.000Z",
      "orderDate": "2021-09-11T09:09:00.000Z",
      "link": {
        "path": "/content/chelseafc/en/news/2021/09/11/thiago-silva-cleared-for-chelsea-action",
        "type": "NewsCard",
        "title": "Thiago Silva cleared for Chelsea action",
        "url": "https://prod-content-cdn.chelseafc.com/content/chelseafc/en/news/2021/09/11/thiago-silva-cleared-for-chelsea-action.html",
        "external": true,
        "target": "sameWindow",
        "categories": [],
        "timestamp": "2021-09-11T09:09:00.000Z"
      },
      "template": "cope-article",
      "path": "/content/chelseafc/en/news/2021/09/11/thiago-silva-cleared-for-chelsea-action",
      "media": {
        "type": "image-component",
        "image": {
          "type": "ImageCloudinary",
          "alt": " ",
          "id": "chelsea-app/Thiago-Silva-stock-GettyImages-1337905612",
          "gravity": "auto",
          "aspectRatio": 1.5004481,
          "cropMode": "fill"
        }
      },
      "content": "Thiago Silva cleared for Chelsea action",
      "publishDate": "2021-09-11T09:09:00.000Z",
      "url": "https://prod-content-cdn.chelseafc.com/content/chelseafc/en/news/2021/09/11/thiago-silva-cleared-for-chelsea-action.html",
      "readTimeInMins": 6,
      "tags": [
        {
          "title": "Thiago Silva",
          "namespace": "content-tag:",
          "id": "content-tag_person_player_thiago-silva"
        }
      ],
      "date": "2021-09-11T09:09:00.000Z",
      "description": "Thiago Silva is available for selection for today’s home match against Aston Villa.",
      "matchId": 2210303
    },
    {
      "contentType": "Competitions",
      "id": "_content_chelseafcennews20210909pre-match-quiz--goals-galore-ver",
      "type": "NewsCard",
      "timestamp": "2021-09-11T09:58:00.000Z",
      "orderDate": "2021-09-11T07:58:00.000Z",
      "link": {
        "path": "/content/chelseafc/en/news/2021/09/09/pre-match-quiz--goals-galore-versus-villa",
        "type": "NewsCard",
        "title": "Pre-match quiz: Goals galore versus Villa",
        "url": "https://prod-content-cdn.chelseafc.com/content/chelseafc/en/news/2021/09/09/pre-match-quiz--goals-galore-versus-villa.html",
        "external": true,
        "target": "sameWindow",
        "categories": [],
        "timestamp": "2021-09-11T09:58:00.000Z"
      },
      "template": "standard-article",
      "path": "/content/chelseafc/en/news/2021/09/09/pre-match-quiz--goals-galore-versus-villa",
      "media": {
        "type": "image-component",
        "image": {
          "type": "ImageCloudinary",
          "alt": "Hazard",
          "id": "editorial/news/2021/09/09/Hazard_Villa_GettyImages-177160985",
          "gravity": "auto",
          "aspectRatio": 1.7773836,
          "cropMode": "fill"
        }
      },
      "content": "Pre-match quiz: Goals galore versus Villa",
      "publishDate": "2021-09-11T09:58:00.000Z",
      "url": "https://prod-content-cdn.chelseafc.com/content/chelseafc/en/news/2021/09/09/pre-match-quiz--goals-galore-versus-villa.html",
      "readTimeInMins": 4,
      "tags": [
        {
          "title": "Premier League",
          "namespace": "content-tag:",
          "id": "content-tag_competition_first-team-competitions_premier-league"
        },
        {
          "title": "Men",
          "namespace": "content-tag:",
          "id": "content-tag_team_men"
        },
        {
          "title": "Aston Villa",
          "namespace": "content-tag:",
          "id": "content-tag_team_opposition-teams_aston-villa"
        },
        {
          "title": "Play Predictor",
          "namespace": "content-tag:",
          "id": "content-tag_features_play-predictor"
        }
      ],
      "date": "2021-09-11T09:58:00.000Z",
      "description": "We have enjoyed some pretty good days in front of goal against Aston Villa at Stamford Bridge. Get ready for Saturday’s game by testing your knowledge of some of those high-scoring matches…",
      "matchId": 2210303
    },
    {
      "contentType": "News",
      "id": "_content_chelseafcennews20210911tuchel--possible-for-saul-to-pla",
      "type": "NewsCard",
      "timestamp": "2021-09-11T03:30:00.000Z",
      "orderDate": "2021-09-11T03:30:00.000Z",
      "link": {
        "path": "/content/chelseafc/en/news/2021/09/11/tuchel--possible-for-saul-to-play-and-i-ll-give-support-to-barkl",
        "type": "NewsCard",
        "title": "Tuchel: Possible for Saul to play and I’ll give support to Barkley",
        "url": "https://prod-content-cdn.chelseafc.com/content/chelseafc/en/news/2021/09/11/tuchel--possible-for-saul-to-play-and-i-ll-give-support-to-barkl.html",
        "external": true,
        "target": "sameWindow",
        "categories": [],
        "timestamp": "2021-09-11T03:30:00.000Z"
      },
      "template": "standard-article",
      "path": "/content/chelseafc/en/news/2021/09/11/tuchel--possible-for-saul-to-play-and-i-ll-give-support-to-barkl",
      "media": {
        "type": "image-component",
        "image": {
          "type": "ImageCloudinary",
          "alt": "Saul in training at Cobham",
          "id": "chelsea-app/Saul-training-GettyImages-1337906611",
          "gravity": "auto",
          "aspectRatio": 1.5025011,
          "cropMode": "fill"
        }
      },
      "content": "Tuchel: Possible for Saul to play and I’ll give support to Barkley",
      "publishDate": "2021-09-11T03:30:00.000Z",
      "url": "https://prod-content-cdn.chelseafc.com/content/chelseafc/en/news/2021/09/11/tuchel--possible-for-saul-to-play-and-i-ll-give-support-to-barkl.html",
      "readTimeInMins": 13,
      "tags": [
        {
          "title": "Thomas Tuchel",
          "namespace": "content-tag:",
          "id": "content-tag_person_manager_thomas-tuchel"
        },
        {
          "title": "Premier League",
          "namespace": "content-tag:",
          "id": "content-tag_competition_first-team-competitions_premier-league"
        },
        {
          "title": "Men",
          "namespace": "content-tag:",
          "id": "content-tag_team_men"
        },
        {
          "title": "Saul Niguez",
          "namespace": "content-tag:",
          "id": "content-tag_person_player_saul-niguez"
        },
        {
          "title": "Ross Barkley",
          "namespace": "content-tag:",
          "id": "content-tag_person_player_ross-barkley"
        },
        {
          "title": "Aston Villa",
          "namespace": "content-tag:",
          "id": "content-tag_team_opposition-teams_aston-villa"
        }
      ],
      "date": "2021-09-11T03:30:00.000Z",
      "description": "Stamford Bridge could witness a debut today Thomas Tuchel has confirmed, and if it happens, it will be a bow in addition to Romelu Lukaku’s possible ‘second home debut’ as a Chelsea player.",
      "matchId": 2210303
    },
    {
      "contentType": "Match Preview",
      "id": "_content_chelseafcennews20210911chelsea-women-v-everton-women-pr",
      "type": "NewsCard",
      "timestamp": "2021-09-11T06:09:00.000Z",
      "orderDate": "2021-09-10T23:09:00.000Z",
      "link": {
        "path": "/content/chelseafc/en/news/2021/09/11/chelsea-women-v-everton-women-preview--kick-off-time--how-to-fol0",
        "type": "NewsCard",
        "title": "Chelsea Women v Everton Women preview: Kick-off time, how to follow and much more",
        "url": "https://prod-content-cdn.chelseafc.com/content/chelseafc/en/news/2021/09/11/chelsea-women-v-everton-women-preview--kick-off-time--how-to-fol0.html",
        "external": true,
        "target": "sameWindow",
        "categories": [],
        "timestamp": "2021-09-11T06:09:00.000Z"
      },
      "template": "cope-article",
      "path": "/content/chelseafc/en/news/2021/09/11/chelsea-women-v-everton-women-preview--kick-off-time--how-to-fol0",
      "media": {
        "type": "image-component",
        "image": {
          "type": "ImageCloudinary",
          "alt": "  ",
          "id": "editorial/women's-team/GettyImages-1307636425",
          "gravity": "auto",
          "aspectRatio": 1.4406091,
          "cropMode": "fill"
        }
      },
      "content": "Chelsea Women v Everton Women preview: Kick-off time, how to follow and much more",
      "publishDate": "2021-09-11T06:09:00.000Z",
      "url": "https://prod-content-cdn.chelseafc.com/content/chelseafc/en/news/2021/09/11/chelsea-women-v-everton-women-preview--kick-off-time--how-to-fol0.html",
      "readTimeInMins": 7,
      "tags": [
        {
          "title": "Women",
          "namespace": "content-tag:",
          "id": "content-tag_team_women"
        }
      ],
      "date": "2021-09-11T06:09:00.000Z",
      "description": "Chelsea Women welcome Everton to Kingsmeadow tomorrow for our first home game of the new Barclays FA Women’s Super League campaign. Here we preview the game and explain how you can follow all the action…"
    },
    {
      "contentType": "News",
      "id": "_content_chelseafcennews20210910important-information-for-attend",
      "type": "NewsCard",
      "timestamp": "2021-09-09T16:19:00.000Z",
      "orderDate": "2021-09-10T19:26:00.000Z",
      "link": {
        "path": "/content/chelseafc/en/news/2021/09/10/important-information-for-attending-games-at-stamford-bridge-and",
        "type": "NewsCard",
        "title": "Important information for attending games at Stamford Bridge and Kingsmeadow",
        "url": "https://prod-content-cdn.chelseafc.com/content/chelseafc/en/news/2021/09/10/important-information-for-attending-games-at-stamford-bridge-and.html",
        "external": true,
        "target": "sameWindow",
        "categories": [],
        "timestamp": "2021-09-09T16:19:00.000Z"
      },
      "template": "cope-article",
      "path": "/content/chelseafc/en/news/2021/09/10/important-information-for-attending-games-at-stamford-bridge-and",
      "media": {
        "type": "image-component",
        "image": {
          "type": "ImageCloudinary",
          "alt": " Stamford Bridge",
          "id": "editorial/news/2021/09/07/stamford-bridge-view-inside-sunny",
          "gravity": "auto",
          "aspectRatio": 1.5001523,
          "cropMode": "fill"
        }
      },
      "content": "Important information for attending games at Stamford Bridge and Kingsmeadow",
      "publishDate": "2021-09-09T16:19:00.000Z",
      "url": "https://prod-content-cdn.chelseafc.com/content/chelseafc/en/news/2021/09/10/important-information-for-attending-games-at-stamford-bridge-and.html",
      "readTimeInMins": 5,
      "tags": [
        {
          "title": "Premier League",
          "namespace": "content-tag:",
          "id": "content-tag_competition_first-team-competitions_premier-league"
        },
        {
          "title": "Men",
          "namespace": "content-tag:",
          "id": "content-tag_team_men"
        },
        {
          "title": "Stamford Bridge",
          "namespace": "content-tag:",
          "id": "content-tag_custom_stamford-bridge"
        },
        {
          "title": "Women",
          "namespace": "content-tag:",
          "id": "content-tag_team_women"
        },
        {
          "title": "Women's Super League",
          "namespace": "content-tag:",
          "id": "content-tag_competition_ladies-competitions_wsl"
        }
      ],
      "date": "2021-09-09T16:19:00.000Z",
      "description": "Regulation changes for this season mean all supporters visiting our stadiums should be aware of the following information."
    },
    {
      "contentType": "Interview",
      "id": "_content_chelseafcennews20210910alonso-exclusive-and-tribute-to-",
      "type": "NewsCard",
      "timestamp": "2021-09-10T09:47:00.000Z",
      "orderDate": "2021-09-10T18:07:00.000Z",
      "link": {
        "path": "/content/chelseafc/en/news/2021/09/10/alonso-exclusive-and-tribute-to-sean-lock-in-matchday-programme",
        "type": "NewsCard",
        "title": "Alonso exclusive and tribute to Sean Lock in matchday programme",
        "url": "https://prod-content-cdn.chelseafc.com/content/chelseafc/en/news/2021/09/10/alonso-exclusive-and-tribute-to-sean-lock-in-matchday-programme.html",
        "external": true,
        "target": "sameWindow",
        "categories": [],
        "timestamp": "2021-09-10T09:47:00.000Z"
      },
      "template": "cope-article",
      "path": "/content/chelseafc/en/news/2021/09/10/alonso-exclusive-and-tribute-to-sean-lock-in-matchday-programme",
      "media": {
        "type": "image-component",
        "image": {
          "type": "ImageCloudinary",
          "alt": " Alonso",
          "id": "editorial/news/2021/09/10/Alonso_GettyImages-1337905337",
          "gravity": "auto",
          "aspectRatio": 1.5028117,
          "cropMode": "fill"
        }
      },
      "content": "Alonso exclusive and tribute to Sean Lock in matchday programme",
      "publishDate": "2021-09-10T09:47:00.000Z",
      "url": "https://prod-content-cdn.chelseafc.com/content/chelseafc/en/news/2021/09/10/alonso-exclusive-and-tribute-to-sean-lock-in-matchday-programme.html",
      "readTimeInMins": 9,
      "tags": [
        {
          "title": "Premier League",
          "namespace": "content-tag:",
          "id": "content-tag_competition_first-team-competitions_premier-league"
        },
        {
          "title": "Programmes",
          "namespace": "content-tag:",
          "id": "content-tag_custom_programmes"
        },
        {
          "title": "Men",
          "namespace": "content-tag:",
          "id": "content-tag_team_men"
        },
        {
          "title": "Aston Villa",
          "namespace": "content-tag:",
          "id": "content-tag_team_opposition-teams_aston-villa"
        },
        {
          "title": "Marcos Alonso",
          "namespace": "content-tag:",
          "id": "content-tag_person_player_marcos-alonso"
        }
      ],
      "date": "2021-09-10T09:47:00.000Z",
      "description": "Don’t forget to pick up your copy of the Chelsea matchday programme when you arrive at Stamford Bridge for the game against Aston Villa.",
      "matchId": 2210303
    },
    {
      "contentType": "Interview",
      "id": "_content_chelseafcennews20210910tuchel-excited-by-saul-addition-",
      "type": "NewsCard",
      "timestamp": "2021-09-10T13:28:00.000Z",
      "orderDate": "2021-09-10T13:28:00.000Z",
      "link": {
        "path": "/content/chelseafc/en/news/2021/09/10/tuchel-excited-by-saul-addition-and-attacking-possibilities",
        "type": "NewsCard",
        "title": "Tuchel excited by Saul addition and attacking possibilities",
        "url": "https://prod-content-cdn.chelseafc.com/content/chelseafc/en/news/2021/09/10/tuchel-excited-by-saul-addition-and-attacking-possibilities.html",
        "external": true,
        "target": "sameWindow",
        "categories": [],
        "timestamp": "2021-09-10T13:28:00.000Z"
      },
      "template": "standard-article",
      "path": "/content/chelseafc/en/news/2021/09/10/tuchel-excited-by-saul-addition-and-attacking-possibilities",
      "media": {
        "type": "image-component",
        "image": {
          "type": "ImageCloudinary",
          "alt": "Tuchel",
          "id": "editorial/news/2021/09/10/Tuchel_DAZ_0022",
          "gravity": "auto",
          "aspectRatio": 1.5,
          "cropMode": "fill"
        }
      },
      "content": "Tuchel excited by Saul addition and attacking possibilities",
      "publishDate": "2021-09-10T13:28:00.000Z",
      "url": "https://prod-content-cdn.chelseafc.com/content/chelseafc/en/news/2021/09/10/tuchel-excited-by-saul-addition-and-attacking-possibilities.html",
      "readTimeInMins": 12,
      "tags": [
        {
          "title": "Timo Werner",
          "namespace": "content-tag:",
          "id": "content-tag_person_player_timo-werner"
        },
        {
          "title": "Thomas Tuchel",
          "namespace": "content-tag:",
          "id": "content-tag_person_manager_thomas-tuchel"
        },
        {
          "title": "Saul Niguez",
          "namespace": "content-tag:",
          "id": "content-tag_person_player_saul-niguez"
        },
        {
          "title": "Aston Villa",
          "namespace": "content-tag:",
          "id": "content-tag_team_opposition-teams_aston-villa"
        },
        {
          "title": "Romelu Lukaku",
          "namespace": "content-tag:",
          "id": "content-tag_person_player_romelu-lukaku"
        },
        {
          "title": "Premier League",
          "namespace": "content-tag:",
          "id": "content-tag_competition_first-team-competitions_premier-league"
        },
        {
          "title": "Men",
          "namespace": "content-tag:",
          "id": "content-tag_team_men"
        }
      ],
      "date": "2021-09-10T13:28:00.000Z",
      "description": "Saul could make his Chelsea debut tomorrow and ahead of that fixture against Aston Villa Thomas Tuchel explained why he was so keen to bring the midfielder to Chelsea.",
      "matchId": 2210303
    },
    {
      "contentType": "News",
      "id": "_content_chelseafcennews20210910thomas-tuchel-issues-chelsea-inj",
      "type": "NewsCard",
      "timestamp": "2021-09-10T13:11:00.000Z",
      "orderDate": "2021-09-10T13:11:00.000Z",
      "link": {
        "path": "/content/chelseafc/en/news/2021/09/10/thomas-tuchel-issues-chelsea-injury-update-",
        "type": "NewsCard",
        "title": "Tuchel: Two out, one available and one maybe for Villa game",
        "url": "https://prod-content-cdn.chelseafc.com/content/chelseafc/en/news/2021/09/10/thomas-tuchel-issues-chelsea-injury-update-.html",
        "external": true,
        "target": "sameWindow",
        "categories": [],
        "timestamp": "2021-09-10T13:11:00.000Z"
      },
      "template": "standard-article",
      "path": "/content/chelseafc/en/news/2021/09/10/thomas-tuchel-issues-chelsea-injury-update-",
      "media": {
        "type": "image-component",
        "image": {
          "type": "ImageCloudinary",
          "alt": "Kante and Pulisic",
          "id": "editorial/news/2021/09/14/kante-pulisic-training",
          "gravity": "auto",
          "aspectRatio": 1.4998308,
          "cropMode": "fill"
        }
      },
      "content": "Tuchel: Two out, one available and one maybe for Villa game",
      "publishDate": "2021-09-10T13:11:00.000Z",
      "url": "https://prod-content-cdn.chelseafc.com/content/chelseafc/en/news/2021/09/10/thomas-tuchel-issues-chelsea-injury-update-.html",
      "readTimeInMins": 5,
      "tags": [
        {
          "title": "Premier League",
          "namespace": "content-tag:",
          "id": "content-tag_competition_first-team-competitions_premier-league"
        },
        {
          "title": "Thomas Tuchel",
          "namespace": "content-tag:",
          "id": "content-tag_person_manager_thomas-tuchel"
        },
        {
          "title": "Men",
          "namespace": "content-tag:",
          "id": "content-tag_team_men"
        },
        {
          "title": "Aston Villa",
          "namespace": "content-tag:",
          "id": "content-tag_team_opposition-teams_aston-villa"
        }
      ],
      "date": "2021-09-10T13:11:00.000Z",
      "description": "Thomas Tuchel was back on media duty at Cobham this afternoon ahead of our return to Premier League action, and the boss issued an update on four Chelsea players’ availability for the meeting with Aston Villa at Stamford Bridge tomorrow.",
      "matchId": 2210303
    },
    {
      "contentType": "Match Preview",
      "id": "_content_chelseafcennews20210910hayes-targets-three-points-again",
      "type": "NewsCard",
      "timestamp": "2021-09-10T16:00:00.000Z",
      "orderDate": "2021-09-10T11:12:00.000Z",
      "link": {
        "path": "/content/chelseafc/en/news/2021/09/10/hayes-targets-three-points-against-the-toffees",
        "type": "NewsCard",
        "title": "Hayes targets three points against the Toffees",
        "url": "https://prod-content-cdn.chelseafc.com/content/chelseafc/en/news/2021/09/10/hayes-targets-three-points-against-the-toffees.html",
        "external": true,
        "target": "sameWindow",
        "categories": [],
        "timestamp": "2021-09-10T16:00:00.000Z"
      },
      "template": "cope-article",
      "path": "/content/chelseafc/en/news/2021/09/10/hayes-targets-three-points-against-the-toffees",
      "media": {
        "type": "image-component",
        "image": {
          "type": "ImageCloudinary",
          "alt": " ",
          "id": "editorial/women's-team/ChelseaWomen_Emma_Hayes_Arsenal_Awy",
          "gravity": "auto",
          "aspectRatio": 1.5,
          "cropMode": "fill"
        }
      },
      "content": "Hayes targets three points against the Toffees",
      "publishDate": "2021-09-10T16:00:00.000Z",
      "url": "https://prod-content-cdn.chelseafc.com/content/chelseafc/en/news/2021/09/10/hayes-targets-three-points-against-the-toffees.html",
      "readTimeInMins": 8,
      "tags": [
        {
          "title": "Emma Hayes",
          "namespace": "content-tag:",
          "id": "content-tag_person_manager_emma-hayes"
        },
        {
          "title": "Women",
          "namespace": "content-tag:",
          "id": "content-tag_team_women"
        },
        {
          "title": "Women's Super League",
          "namespace": "content-tag:",
          "id": "content-tag_competition_ladies-competitions_wsl"
        },
        {
          "title": "Everton",
          "namespace": "content-tag:",
          "id": "content-tag_team_opposition-teams_everton"
        }
      ],
      "date": "2021-09-10T16:00:00.000Z",
      "description": "Emma Hayes is excited about the return of our Blues fans for this weekend’s game against Everton at Kingsmeadow.",
      "matchId": 2236324
    }
  ]
}
