{
  "items": [
    {
      "id": "1GFiOxtgu7sce87A0QHCM7",
      "title": "Pulisic: Good performance but still work to do",
      "type": "Article",
      "category": {
        "id": "1c71f05f-27c7-4d9c-8dbd-8e2e532c5fed",
        "title": "Men's Team",
        "url": "/en/news/category/mens-team",
        "isExternal": false,
        "isActive": false
      },
      "date": "2022-11-26T12:05:00.0000000+00:00",
      "url": "/en/news/article/pulisic-good-performance-but-still-work-to-do",
      "link": null,
      "thumbnail": {
        "id": "editorial/news/2022/11/26/Pulisic-USA-vs-England-WC22",
        "title": "editorial/news/2022/11/26/Pulisic-USA-vs-England-WC22",
        "description": "",
        "credit": "",
        "file": {
          "fileName": "editorial/news/2022/11/26/Pulisic-USA-vs-England-WC22",
          "contentType": "image",
          "type": "upload",
          "format": "jpg",
          "url": "http://img.chelseafc.com/image/upload/v1669462343/editorial/news/2022/11/26/Pulisic-USA-vs-England-WC22.jpg",
          "urlObject": {
            "baseUrl": "https://res.cloudinary.com/",
            "cloudName": "chelsea-production",
            "resourceType": "image",
            "type": "upload",
            "publicId": "editorial/news/2022/11/26/Pulisic-USA-vs-England-WC22"
          },
          "details": {
            "size": 10173345,
            "transformations": "",
            "image": {
              "width": 4573,
              "height": 3048
            }
          }
        },
        "coordinates": []
      },
      "videoId": null,
      "articleType": null,
      "matchId": null,
      "isBoxSet": false,
      "newsType": null
    },
    {
      "id": "6thU3IfNUUsho5Px8Zy6wx",
      "title": "Kai Havertz's World Cup favourites",
      "type": "Article",
      "category": {
        "id": "6483435d-0eda-41a3-961c-e3815086fbfa",
        "title": "Internationals",
        "url": "/en/news/category/internationals",
        "isExternal": false,
        "isActive": false
      },
      "date": "2022-11-26T06:00:00.0000000+00:00",
      "url": "/en/news/article/kai-havertzs-world-cup-favourites",
      "link": null,
      "thumbnail": {
        "id": "editorial/news/2022/11/25/Havertz_Germany_World_Cup_pose",
        "title": "editorial/news/2022/11/25/Havertz_Germany_World_Cup_pose",
        "description": "",
        "credit": "",
        "file": {
          "fileName": "editorial/news/2022/11/25/Havertz_Germany_World_Cup_pose",
          "contentType": "image",
          "type": "upload",
          "format": "jpg",
          "url": "http://img.chelseafc.com/image/upload/v1669385876/editorial/news/2022/11/25/Havertz_Germany_World_Cup_pose.jpg",
          "urlObject": {
            "baseUrl": "https://res.cloudinary.com/",
            "cloudName": "chelsea-production",
            "resourceType": "image",
            "type": "upload",
            "publicId": "editorial/news/2022/11/25/Havertz_Germany_World_Cup_pose"
          },
          "details": {
            "size": 9214868,
            "transformations": "",
            "image": {
              "width": 3265,
              "height": 4898
            }
          }
        },
        "coordinates": []
      },
      "videoId": null,
      "articleType": null,
      "matchId": null,
      "isBoxSet": false,
      "newsType": null
    },
    {
      "id": "36HuZ8uazHrnJtqjDnKxUG",
      "title": "Under-18s report: Chelsea 1 Fulham 7",
      "type": "Article",
      "category": {
        "id": "286165f4-8022-402b-9bfd-38b0f22fb44f",
        "title": "U18s",
        "url": "/en/news/category/u18s",
        "isExternal": false,
        "isActive": false
      },
      "date": "2022-11-26T00:30:00.0000000+00:00",
      "url": "/en/news/article/under-18s-report-chelsea-1-fulham-7",
      "link": null,
      "thumbnail": {
        "id": "editorial/Leo_Castledine_action_shot__action_shot_under_18s_PL_Fulham_22_23",
        "title": "editorial/Leo_Castledine_action_shot__action_shot_under_18s_PL_Fulham_22_23",
        "description": "",
        "credit": "",
        "file": {
          "fileName": "editorial/Leo_Castledine_action_shot__action_shot_under_18s_PL_Fulham_22_23",
          "contentType": "image",
          "type": "upload",
          "format": "jpg",
          "url": "http://img.chelseafc.com/image/upload/v1669468296/editorial/Leo_Castledine_action_shot__action_shot_under_18s_PL_Fulham_22_23.jpg",
          "urlObject": {
            "baseUrl": "https://res.cloudinary.com/",
            "cloudName": "chelsea-production",
            "resourceType": "image",
            "type": "upload",
            "publicId": "editorial/Leo_Castledine_action_shot__action_shot_under_18s_PL_Fulham_22_23"
          },
          "details": {
            "size": 3208904,
            "transformations": "",
            "image": {
              "width": 5000,
              "height": 3333
            }
          }
        },
        "coordinates": []
      },
      "videoId": null,
      "articleType": null,
      "matchId": "53pr0s99KDIEVgI4zTpo3d",
      "isBoxSet": false,
      "newsType": null
    },
    {
      "id": "3dWIuFrBQOMvQ2OUrWf2rp",
      "title": "Local pupils take part in environmental challenge  ",
      "type": "Article",
      "category": {
        "id": "986ceb9e-8288-4c00-8db0-d5f36ef3d6fe",
        "title": "Foundation",
        "url": "/en/news/category/foundation",
        "isExternal": false,
        "isActive": false
      },
      "date": "2022-11-26T00:30:00.0000000+00:00",
      "url": "/en/news/article/local-pupils-take-part-in-environmental-challenge",
      "link": null,
      "thumbnail": {
        "id": "editorial/news/2022/11/25/Premier_League_Inspires_programme_2",
        "title": "editorial/news/2022/11/25/Premier_League_Inspires_programme_2",
        "description": "",
        "credit": "",
        "file": {
          "fileName": "editorial/news/2022/11/25/Premier_League_Inspires_programme_2",
          "contentType": "image",
          "type": "upload",
          "format": "jpg",
          "url": "http://img.chelseafc.com/image/upload/v1669383302/editorial/news/2022/11/25/Premier_League_Inspires_programme_2.jpg",
          "urlObject": {
            "baseUrl": "https://res.cloudinary.com/",
            "cloudName": "chelsea-production",
            "resourceType": "image",
            "type": "upload",
            "publicId": "editorial/news/2022/11/25/Premier_League_Inspires_programme_2"
          },
          "details": {
            "size": 294864,
            "transformations": "",
            "image": {
              "width": 757,
              "height": 502
            }
          }
        },
        "coordinates": []
      },
      "videoId": null,
      "articleType": null,
      "matchId": null,
      "isBoxSet": false,
      "newsType": null
    },
    {
      "id": "CtC1SFsryhirgas8Kgkdv",
      "title": "Under-18s preview: Young Blues take on Fulham after U17s progress",
      "type": "Article",
      "category": {
        "id": "9a3fd6e5-c005-43d0-945f-a6a1543ca809",
        "title": "U18s",
        "url": "/en/news/category/u18s",
        "isExternal": false,
        "isActive": false
      },
      "date": "2022-11-26T00:01:00.0000000+00:00",
      "url": "/en/news/article/under-18s-preview-young-blues-take-on-fulham-after-u17s-progress",
      "link": null,
      "thumbnail": {
        "id": "editorial/news/2022/09/15/Brand-U19s-Salzburg-h",
        "title": "editorial/news/2022/09/15/Brand-U19s-Salzburg-h",
        "description": "",
        "credit": "",
        "file": {
          "fileName": "editorial/news/2022/09/15/Brand-U19s-Salzburg-h",
          "contentType": "image",
          "type": "upload",
          "format": "jpg",
          "url": "http://img.chelseafc.com/image/upload/v1663247848/editorial/news/2022/09/15/Brand-U19s-Salzburg-h.jpg",
          "urlObject": {
            "baseUrl": "https://res.cloudinary.com/",
            "cloudName": "chelsea-production",
            "resourceType": "image",
            "type": "upload",
            "publicId": "editorial/news/2022/09/15/Brand-U19s-Salzburg-h"
          },
          "details": {
            "size": 2336807,
            "transformations": "",
            "image": {
              "width": 5000,
              "height": 3333
            }
          }
        },
        "coordinates": []
      },
      "videoId": null,
      "articleType": null,
      "matchId": "53pr0s99KDIEVgI4zTpo3d",
      "isBoxSet": false,
      "newsType": null
    },
    {
      "id": "1MCSMUvI9SJgHcwoFVAjLm",
      "title": "Conor & Erin: Best Friends! | Chelsea Trending",
      "type": "Video",
      "category": {
        "id": "9a64fddc-e0c4-42d4-b269-b92d51452c7d",
        "title": "Video",
        "url": "/en/news/category/video",
        "isExternal": false,
        "isActive": false
      },
      "date": "2022-11-26T00:01:00.0000000+00:00",
      "url": "/en/video/conor-and-erin-best-friends-or-chelsea-trending",
      "link": null,
      "thumbnail": {
        "id": "video/2022/11/26/maxresdefault_1",
        "title": "video/2022/11/26/maxresdefault_1",
        "description": "",
        "credit": "",
        "file": {
          "fileName": "video/2022/11/26/maxresdefault_1",
          "contentType": "image",
          "type": "upload",
          "format": "jpg",
          "url": "http://img.chelseafc.com/image/upload/v1669471277/video/2022/11/26/maxresdefault_1.jpg",
          "urlObject": {
            "baseUrl": "https://res.cloudinary.com/",
            "cloudName": "chelsea-production",
            "resourceType": "image",
            "type": "upload",
            "publicId": "video/2022/11/26/maxresdefault_1"
          },
          "details": {
            "size": 121969,
            "transformations": "",
            "image": {
              "width": 1280,
              "height": 720
            }
          }
        },
        "coordinates": []
      },
      "videoId": "VcEGK0nF",
      "articleType": null,
      "matchId": null,
      "isBoxSet": false,
      "newsType": null
    },
    {
      "id": "5wweDjZ2Jfra9vw3TZmxAL",
      "title": "World Cup: Pulisic named Player of the Match as England and USA can't be separated",
      "type": "Article",
      "category": {
        "id": "ee2900df-843f-4576-8514-a8493e8a7579",
        "title": "Internationals",
        "url": "/en/news/category/internationals",
        "isExternal": false,
        "isActive": false
      },
      "date": "2022-11-25T21:00:00.0000000+00:00",
      "url": "/en/news/article/world-cup-england-and-usa-cant-be-separated-in-second-group-game",
      "link": null,
      "thumbnail": {
        "id": "editorial/news/2022/11/25/England_USA_Pulisic_2",
        "title": "editorial/news/2022/11/25/England_USA_Pulisic_2",
        "description": "",
        "credit": "",
        "file": {
          "fileName": "editorial/news/2022/11/25/England_USA_Pulisic_2",
          "contentType": "image",
          "type": "upload",
          "format": "jpg",
          "url": "http://img.chelseafc.com/image/upload/v1669408306/editorial/news/2022/11/25/England_USA_Pulisic_2.jpg",
          "urlObject": {
            "baseUrl": "https://res.cloudinary.com/",
            "cloudName": "chelsea-production",
            "resourceType": "image",
            "type": "upload",
            "publicId": "editorial/news/2022/11/25/England_USA_Pulisic_2"
          },
          "details": {
            "size": 9920381,
            "transformations": "",
            "image": {
              "width": 4338,
              "height": 2892
            }
          }
        },
        "coordinates": []
      },
      "videoId": null,
      "articleType": null,
      "matchId": null,
      "isBoxSet": false,
      "newsType": null
    },
    {
      "id": "7djjwTdV7ivpU5c0F990Lr",
      "title": "FIVE points clear at top of UWCL group! | Unseen Extra",
      "type": "Video",
      "category": {
        "id": "7d5efe3b-0d64-4a81-b5eb-f27f5adb74aa",
        "title": "Video",
        "url": "/en/news/category/video",
        "isExternal": false,
        "isActive": false
      },
      "date": "2022-11-25T20:00:00.0000000+00:00",
      "url": "/en/video/chelsea-women-vs-real-madrid-2-0-or-unseen-extra-or-uwcl",
      "link": null,
      "thumbnail": {
        "id": "video/2022/11/25/251122_UE_W",
        "title": "video/2022/11/25/251122_UE_W",
        "description": "",
        "credit": "",
        "file": {
          "fileName": "video/2022/11/25/251122_UE_W",
          "contentType": "image",
          "type": "upload",
          "format": "jpg",
          "url": "http://img.chelseafc.com/image/upload/v1669379537/video/2022/11/25/251122_UE_W.jpg",
          "urlObject": {
            "baseUrl": "https://res.cloudinary.com/",
            "cloudName": "chelsea-production",
            "resourceType": "image",
            "type": "upload",
            "publicId": "video/2022/11/25/251122_UE_W"
          },
          "details": {
            "size": 956623,
            "transformations": "",
            "image": {
              "width": 1920,
              "height": 1080
            }
          }
        },
        "coordinates": []
      },
      "videoId": "5vrLBlZp",
      "articleType": null,
      "matchId": "2cBntwEKeYbEOU0qyNDjhW",
      "isBoxSet": false,
      "newsType": null
    },
    {
      "id": "4KnzaKJ2BbjUXTrdBJLaEy",
      "title": "📝 Trevoh Chalobah signs until 2028!",
      "type": "Video",
      "category": {
        "id": "28633f18-8f81-4a75-b472-4a72adc369df",
        "title": "Video",
        "url": "/en/news/category/video",
        "isExternal": false,
        "isActive": false
      },
      "date": "2022-11-25T11:21:58.0100000+00:00",
      "url": "/en/video/trevoh-chalobah-signs-contract-extension",
      "link": null,
      "thumbnail": {
        "id": "video/2022/11/25/GettyImages-1344434533",
        "title": "video/2022/11/25/GettyImages-1344434533",
        "description": "",
        "credit": "",
        "file": {
          "fileName": "video/2022/11/25/GettyImages-1344434533",
          "contentType": "image",
          "type": "upload",
          "format": "jpg",
          "url": "http://img.chelseafc.com/image/upload/v1669376541/video/2022/11/25/GettyImages-1344434533.jpg",
          "urlObject": {
            "baseUrl": "https://res.cloudinary.com/",
            "cloudName": "chelsea-production",
            "resourceType": "image",
            "type": "upload",
            "publicId": "video/2022/11/25/GettyImages-1344434533"
          },
          "details": {
            "size": 2112065,
            "transformations": "",
            "image": {
              "width": 3479,
              "height": 2271
            }
          }
        },
        "coordinates": []
      },
      "videoId": "LkRhCbXl",
      "articleType": null,
      "matchId": null,
      "isBoxSet": false,
      "newsType": null
    },
    {
      "id": "10ea1CGrRamYWFvak8pzm3",
      "title": "New long-term contract for Chalobah",
      "type": "Article",
      "category": {
        "id": "49b7d36f-2e6c-42f8-a382-79102e368037",
        "title": "Men's Team",
        "url": "/en/news/category/mens-team",
        "isExternal": false,
        "isActive": false
      },
      "date": "2022-11-25T11:00:00.0000000+00:00",
      "url": "/en/news/article/new-long-term-contract-for-chalobah",
      "link": null,
      "thumbnail": {
        "id": "editorial/news/2022/11/24/Chalobah_media_access_day_3",
        "title": "editorial/news/2022/11/24/Chalobah_media_access_day_3",
        "description": "",
        "credit": "",
        "file": {
          "fileName": "editorial/news/2022/11/24/Chalobah_media_access_day_3",
          "contentType": "image",
          "type": "upload",
          "format": "jpg",
          "url": "http://img.chelseafc.com/image/upload/v1669370555/editorial/news/2022/11/24/Chalobah_media_access_day_3.jpg",
          "urlObject": {
            "baseUrl": "https://res.cloudinary.com/",
            "cloudName": "chelsea-production",
            "resourceType": "image",
            "type": "upload",
            "publicId": "editorial/news/2022/11/24/Chalobah_media_access_day_3"
          },
          "details": {
            "size": 5107446,
            "transformations": "",
            "image": {
              "width": 5504,
              "height": 8256
            }
          }
        },
        "coordinates": []
      },
      "videoId": null,
      "articleType": null,
      "matchId": null,
      "isBoxSet": false,
      "newsType": null
    },
    {
      "id": "6x8K8cYD2jKCI0Yn2LwdlU",
      "title": "Everything you need to know about Trevoh Chalobah",
      "type": "Article",
      "category": {
        "id": "11c2881a-fc43-4e89-86f6-c2254d121519",
        "title": "Men's Team",
        "url": "/en/news/category/mens-team",
        "isExternal": false,
        "isActive": false
      },
      "date": "2022-11-25T10:30:00.0000000+00:00",
      "url": "/en/news/article/everything-you-need-to-know-about-trevoh-chalobah",
      "link": null,
      "thumbnail": {
        "id": "editorial/news/2022/11/10/Chalobah_GettyImages-1438750080",
        "title": "editorial/news/2022/11/10/Chalobah_GettyImages-1438750080",
        "description": "",
        "credit": "",
        "file": {
          "fileName": "editorial/news/2022/11/10/Chalobah_GettyImages-1438750080",
          "contentType": "image",
          "type": "upload",
          "format": "jpg",
          "url": "http://img.chelseafc.com/image/upload/v1668086203/editorial/news/2022/11/10/Chalobah_GettyImages-1438750080.jpg",
          "urlObject": {
            "baseUrl": "https://res.cloudinary.com/",
            "cloudName": "chelsea-production",
            "resourceType": "image",
            "type": "upload",
            "publicId": "editorial/news/2022/11/10/Chalobah_GettyImages-1438750080"
          },
          "details": {
            "size": 3148429,
            "transformations": "",
            "image": {
              "width": 5158,
              "height": 3439
            }
          }
        },
        "coordinates": []
      },
      "videoId": null,
      "articleType": null,
      "matchId": null,
      "isBoxSet": false,
      "newsType": null
    },
    {
      "id": "5WSGFCkArn7ADTfwqnkOVC",
      "title": "World Cup: Chelsea duo help Senegal to vital Group A win ",
      "type": "Article",
      "category": {
        "id": "42cbe846-1f94-4f8f-8698-5ad022d83d53",
        "title": "Internationals",
        "url": "/en/news/category/internationals",
        "isExternal": false,
        "isActive": false
      },
      "date": "2022-11-25T10:10:00.0000000+00:00",
      "url": "/en/news/article/world-cup-chelsea-duo-help-senegal-to-vital-group-a-win",
      "link": null,
      "thumbnail": {
        "id": "The 5th Stand app editorial/International tournaments /WORLD CUP 2022/Senegal/GettyImages-1444461775",
        "title": "The 5th Stand app editorial/International tournaments /WORLD CUP 2022/Senegal/GettyImages-1444461775",
        "description": "",
        "credit": "",
        "file": {
          "fileName": "The 5th Stand app editorial/International tournaments /WORLD CUP 2022/Senegal/GettyImages-1444461775",
          "contentType": "image",
          "type": "upload",
          "format": "jpg",
          "url": "http://img.chelseafc.com/image/upload/v1669387300/The%205th%20Stand%20app%20editorial/International%20tournaments%20/WORLD%20CUP%202022/Senegal/GettyImages-1444461775.jpg",
          "urlObject": {
            "baseUrl": "https://res.cloudinary.com/",
            "cloudName": "chelsea-production",
            "resourceType": "image",
            "type": "upload",
            "publicId": "The 5th Stand app editorial/International tournaments /WORLD CUP 2022/Senegal/GettyImages-1444461775"
          },
          "details": {
            "size": 5853361,
            "transformations": "",
            "image": {
              "width": 3326,
              "height": 2357
            }
          }
        },
        "coordinates": []
      },
      "videoId": null,
      "articleType": null,
      "matchId": null,
      "isBoxSet": false,
      "newsType": null
    }
  ],
  "pagination": {
    "totalItems": 15547,
    "itemsPerPage": 12,
    "currentPage": 1,
    "pageItemsCount": 12
  }
}
